LICENSE.txt
MANIFEST.in
README.rst
setup.py
coinbridge/__init__.py
coinbridge/bitcoin-listen
coinbridge/db.py
coinbridge.egg-info/PKG-INFO
coinbridge.egg-info/SOURCES.txt
coinbridge.egg-info/dependency_links.txt
coinbridge.egg-info/requires.txt
coinbridge.egg-info/top_level.txt
coinbridge/data/__init__.py
coinbridge/data/coins.json
coinbridge/data/postgres.json
test/test_bridge.py
test/test_payments.py