Metadata-Version: 1.1
Name: coinbridge
Version: 0.1.4
Summary: Bitcoin/PostgreSQL bridge
Home-page: https://github.com/tinybike/coinbridge
Author: Jack Peterson
Author-email: <jack@tinybike.net>
License: MIT
Download-URL: https://github.com/tinybike/coinbridge/tarball/0.1.4
Keywords: bitcoin,postgres,transaction,bridge
Platform: UNKNOWN
